ecodynalyze/__init__.py
ecodynalyze/main.py
ecodynalyze/prompts.py
ecodynalyze-2025.12.20201125.dist-info/METADATA
ecodynalyze-2025.12.20201125.dist-info/WHEEL
ecodynalyze-2025.12.20201125.dist-info/top_level.txt
ecodynalyze-2025.12.20201125.dist-info/RECORD
