Metadata-Version: 2.4
Name: ecodynalyze
Version: 2025.12.20201125
Summary: A new package designed to analyze and summarize ecological studies, specifically focusing on the dynamics of species interactions. Users input text excerpts from research papers or field notes, and th
Author-email: ecodynalyze <hi@eugene.plus>
License: MIT
Project-URL: Homepage, https://github.com/chigwell/ecodynalyze
Requires-Python: >=3.9
Requires-Dist: langchain-llm7>=0.0.0
Requires-Dist: llmatch-messages>=0.0.0
Requires-Dist: langchain-core>=0.3.0
